{
  "type": "Feature",
  "properties": {
    "iso:country":"CW",
    "name:eng_x_preferred":[
        "Wishi"
    ],
    "name:fra_x_preferred":[
        "Wishi"
    ],
    "name:nld_x_preferred":[
        "Wishi"
    ],
    "name:und_x_variant":[
        "Juicio"
    ],
    "qs:gn_fcode":"PPLX",
    "qs:gn_local":0,
    "qs:gn_namadm1":"00",
    "qs:gn_name":"Wishi",
    "qs:local_max":4398,
    "qs:local_sum":11515,
    "qs:localhoods":9,
    "qs:name":"Wishi",
    "qs:name_adm0":"Cura\u00e7ao",
    "qs:name_local":"Willemstad",
    "qs:photo_max":622,
    "qs:photo_sum":2037,
    "qs:placetype":"Suburb",
    "qs:quad_count":54,
    "qs:woe_adm0":56558057,
    "qs:woe_adm1":0,
    "qs:woe_adm2":0,
    "qs:woe_lau":0,
    "qs:woe_local":152045,
    "qs:woe_ver":"7.10.0",
    "wd:wordcount":270,
    "wof:name":"Wishi",
    "wof:placetype":"neighbourhood"
},
  "geometry": {"coordinates":[-68.960002,12.121633],"type":"Point"}
}