{
  "type": "Feature",
  "properties": {
    "gn:admin1_code":"00",
    "gn:asciiname":"Bona Vista",
    "gn:country_code":"CW",
    "gn:dem":27,
    "gn:feature_class":"P",
    "gn:feature_code":"PPLL",
    "gn:name":"Bona Vista",
    "gn:population":0,
    "gn:timezone":"America/Curacao",
    "iso:country":"CW",
    "wof:name":"Bona Vista",
    "wof:placetype":"locality"
},
  "geometry": {"coordinates":[-68.84999999999999,12.11667],"type":"Point"}
}