{
  "type": "Feature",
  "properties": {
    "iso:country":"CW",
    "name:azb_x_preferred":[
        "\u0622\u0631\u0627\u0631\u0627\u062a"
    ],
    "name:aze_x_preferred":[
        "Ararat"
    ],
    "name:bul_x_preferred":[
        "\u0410\u0440\u0430\u0440\u0430\u0442"
    ],
    "name:cat_x_preferred":[
        "Ararat"
    ],
    "name:ceb_x_preferred":[
        "Ararat"
    ],
    "name:cym_x_preferred":[
        "Ararat"
    ],
    "name:deu_x_preferred":[
        "Ararat"
    ],
    "name:ell_x_preferred":[
        "\u0391\u03c1\u03b1\u03c1\u03ac\u03c4"
    ],
    "name:epo_x_preferred":[
        "Ararat"
    ],
    "name:est_x_preferred":[
        "Ararat"
    ],
    "name:fas_x_preferred":[
        "\u0622\u0631\u0627\u0631\u0627\u062a"
    ],
    "name:fin_x_preferred":[
        "Ararat"
    ],
    "name:fra_x_preferred":[
        "Ararat"
    ],
    "name:hbs_x_preferred":[
        "Ararat"
    ],
    "name:heb_x_preferred":[
        "\u05d0\u05e8\u05e8\u05d8"
    ],
    "name:hrv_x_preferred":[
        "Ararat"
    ],
    "name:hun_x_preferred":[
        "Arar\u00e1t"
    ],
    "name:hye_x_preferred":[
        "\u0531\u0580\u0561\u0580\u0561\u057f"
    ],
    "name:ita_x_preferred":[
        "Ararat"
    ],
    "name:jpn_x_preferred":[
        "\u30a2\u30e9\u30e9\u30c8"
    ],
    "name:kat_x_preferred":[
        "\u10d0\u10e0\u10d0\u10e0\u10d0\u10e2\u10d8"
    ],
    "name:kor_x_preferred":[
        "\uc544\ub77c\ub77c\ud2b8"
    ],
    "name:lit_x_preferred":[
        "Araratas"
    ],
    "name:ltz_x_preferred":[
        "Ararat"
    ],
    "name:mlg_x_preferred":[
        "Ararat"
    ],
    "name:nld_x_preferred":[
        "Ararat"
    ],
    "name:oss_x_preferred":[
        "\u0410\u0440\u0430\u0440\u0430\u0442"
    ],
    "name:pol_x_preferred":[
        "Ararat"
    ],
    "name:por_x_preferred":[
        "Ararate"
    ],
    "name:ron_x_preferred":[
        "Ararat"
    ],
    "name:rus_x_preferred":[
        "\u0410\u0440\u0430\u0440\u0430\u0442"
    ],
    "name:slk_x_preferred":[
        "Ararat"
    ],
    "name:slv_x_preferred":[
        "Ararat"
    ],
    "name:spa_x_preferred":[
        "Ararat"
    ],
    "name:srp_x_preferred":[
        "\u0410\u0440\u0430\u0440\u0430\u0442"
    ],
    "name:swe_x_preferred":[
        "Ararat"
    ],
    "name:tgl_x_preferred":[
        "Ararat"
    ],
    "name:tur_x_preferred":[
        "Ararat"
    ],
    "name:ukr_x_preferred":[
        "\u0410\u0440\u0430\u0440\u0430\u0442"
    ],
    "qs:gn_fcode":"PPLX",
    "qs:gn_local":0,
    "qs:gn_namadm1":"00",
    "qs:gn_name":"Ararat",
    "qs:local_max":4398,
    "qs:local_sum":11515,
    "qs:localhoods":9,
    "qs:name":"Ararat",
    "qs:name_adm0":"Cura\u00e7ao",
    "qs:name_local":"Willemstad",
    "qs:photo_max":211,
    "qs:photo_sum":1473,
    "qs:placetype":"Suburb",
    "qs:quad_count":39,
    "qs:woe_adm0":56558057,
    "qs:woe_adm1":0,
    "qs:woe_adm2":0,
    "qs:woe_lau":0,
    "qs:woe_local":152045,
    "qs:woe_ver":"7.10.0",
    "wd:wordcount":452,
    "wof:lang":[
        "dut"
    ],
    "wof:name":"Ararat",
    "wof:placetype":"neighbourhood"
},
  "geometry": {"coordinates":[-68.929463,12.113572],"type":"Point"}
}