{
  "type": "Feature",
  "properties": {
    "gn:asciiname":"Coral Estate Rif St. Marie",
    "gn:country_code":"CW",
    "gn:dem":73,
    "gn:feature_class":"P",
    "gn:feature_code":"PPL",
    "gn:name":"Coral Estate Rif St. Marie",
    "gn:population":0,
    "gn:timezone":"America/Curacao",
    "iso:country":"CW",
    "wof:name":"Coral Estate Rif St. Marie",
    "wof:placetype":"locality"
},
  "geometry": {"coordinates":[-69.07328000000001,12.20902],"type":"Point"}
}