{
  "type": "Feature",
  "properties": {
    "gn:admin1_code":"00",
    "gn:asciiname":"Dorp Sint Michiel",
    "gn:country_code":"CW",
    "gn:dem":31,
    "gn:feature_class":"P",
    "gn:feature_code":"PPL",
    "gn:name":"Dorp Sint Michiel",
    "gn:population":0,
    "gn:timezone":"America/Curacao",
    "iso:country":"CW",
    "name:und_x_variant":[
        "Sint Michiel",
        "Dorp Sint Michiel"
    ],
    "wof:name":"Dorp Sint Michiel",
    "wof:placetype":"locality"
},
  "geometry": {"coordinates":[-68.98333000000001,12.13333],"type":"Point"}
}