{
  "type": "Feature",
  "properties": {
    "gn:country":"CW",
    "gn:fcode":"PPL",
    "gn:pop":5138,
    "iso:country":"CW",
    "qs:name":"Sint Michiel Liber",
    "qs:photos_9r":0,
    "qs:photos_sr":0,
    "qs:pop_sr":"5",
    "wof:name":"Sint Michiel Liber",
    "wof:placetype":"locality",
    "wof:population":5138
},
  "geometry": {"coordinates":[-68.98333,12.15],"type":"Point"}
}