{
  "type": "Feature",
  "properties": {
    "gn:admin1_code":"00",
    "gn:asciiname":"Weitje",
    "gn:country_code":"CW",
    "gn:dem":-9999,
    "gn:feature_class":"P",
    "gn:feature_code":"PPL",
    "gn:name":"Weitje",
    "gn:population":0,
    "gn:timezone":"America/Curacao",
    "iso:country":"CW",
    "wof:name":"Weitje",
    "wof:placetype":"locality"
},
  "geometry": {"coordinates":[-68.98333000000001,12.01667],"type":"Point"}
}