{
  "type": "Feature",
  "properties": {
    "gn:admin1_code":"00",
    "gn:asciiname":"Kas Chikitu",
    "gn:country_code":"CW",
    "gn:dem":1,
    "gn:feature_class":"P",
    "gn:feature_code":"PPL",
    "gn:name":"Kas Chikitu",
    "gn:population":0,
    "gn:timezone":"America/Curacao",
    "iso:country":"CW",
    "name:und_x_variant":[
        "Cas Chikitoe",
        "Kas Chikitu"
    ],
    "wof:name":"Kas Chikitu",
    "wof:placetype":"locality"
},
  "geometry": {"coordinates":[-68.96666999999999,12.11667],"type":"Point"}
}